eviex/__init__.py
eviex/indexer.py
eviex-0.1.0.dist-info/LICENSE
eviex-0.1.0.dist-info/WHEEL
eviex-0.1.0.dist-info/METADATA
eviex-0.1.0.dist-info/RECORD
