Metadata-Version: 2.1
Name: eviex
Version: 0.1.0
Summary: EVents Inverted indEX
Home-page: https://github.com/se7entyse7en/eviex
License: Apache-2.0
Author: Lou Marvin Caraig
Author-email: loumarvincaraig@gmail.com
Requires-Python: >=3.6.1,<4.0.0
Classifier: License :: OSI Approved :: Apache Software License
Classifier: Programming Language :: Python :: 3
Classifier: Programming Language :: Python :: 3.7
Classifier: Programming Language :: Python :: 3.8
Classifier: Programming Language :: Python :: 3.9
Requires-Dist: numpy (>=1.19.2,<2.0.0)
Requires-Dist: pandas (>=1.1.3,<2.0.0)
Project-URL: Repository, https://github.com/se7entyse7en/eviex
